{
  "authSelections": "userPoolOnly",
  "resourceName": "vai",
  "serviceType": "imported",
  "region": "eu-west-2",
  "usernameAttributes": [
    "email"
  ],
  "requiredAttributes": [
    "given_name",
    "family_name",
    "email",
    "birthdate",
    "locale",
    "phone_number"
  ],
  "passwordPolicyMinLength": 8,
  "passwordPolicyCharacters": [
    "Requires Lowercase",
    "Requires Uppercase",
    "Requires Numbers",
    "Requires Symbols"
  ],
  "mfaConfiguration": "OFF",
  "autoVerifiedAttributes": [
    "email"
  ],
  "mfaTypes": []
}